theseus/__init__.py
theseus/_tracer.py
theseus/_version.py
theseus/test/__init__.py
theseus/test/test_tracer.py
twisted_theseus-0.14.1.3.dist-info/DESCRIPTION.rst
twisted_theseus-0.14.1.3.dist-info/METADATA
twisted_theseus-0.14.1.3.dist-info/RECORD
twisted_theseus-0.14.1.3.dist-info/WHEEL
twisted_theseus-0.14.1.3.dist-info/metadata.json
twisted_theseus-0.14.1.3.dist-info/top_level.txt
