Metadata-Version: 2.0
Name: twisted-theseus
Version: 0.14.1.3
Summary: a Deferred-aware profiler for Twisted
Home-page: https://github.com/flowroute/twisted-theseus
Author: Aaron Gallagher
Author-email: _@habnab.it
License: ISC
Platform: UNKNOWN
Classifier: Development Status :: 2 - Pre-Alpha
Classifier: Framework :: Twisted
Classifier: Intended Audience :: Developers
Classifier: License :: OSI Approved :: ISC License (ISCL)
Classifier: Operating System :: OS Independent
Classifier: Programming Language :: Python :: 2
Classifier: Programming Language :: Python :: 2.6
Classifier: Programming Language :: Python :: 2.7
Classifier: Topic :: Software Development
Requires-Dist: Twisted
